README.rst
setup.py
usncarve.py
usncarve.egg-info/PKG-INFO
usncarve.egg-info/SOURCES.txt
usncarve.egg-info/dependency_links.txt
usncarve.egg-info/top_level.txt