Metadata-Version: 1.1
Name: usncarve
Version: 1.0.0
Summary: A Python script to carve NTFS USN journal records from binary data
Home-page: https://github.com/PoorBillionaire/USN-Record-Carver
Author: Adam Witt
Author-email: accidentalassist@gmail.com
License: Apache Software License
Keywords: DFIR NTFS USN Carve Forensics Incident Response Microsoft Windows
Platform: UNKNOWN
Classifier: Development Status :: 5 - Production/Stable
Classifier: Intended Audience :: Information Technology
Classifier: Topic :: Security
Classifier: License :: OSI Approved :: Apache Software License
